nftl_ed_lms_tools/__init__.py
nftl_ed_lms_tools/client.py
nftl_ed_lms_tools/ed_api.py
nftl_ed_lms_tools/api/__init__.py
nftl_ed_lms_tools/api/usergroups.py
nftl_ed_lms_tools/api/users.py
nftl_ed_lms_tools-0.1.5.dist-info/METADATA
nftl_ed_lms_tools-0.1.5.dist-info/RECORD
nftl_ed_lms_tools-0.1.5.dist-info/WHEEL
nftl_ed_lms_tools-0.1.5.dist-info/top_level.txt
tests/__init__.py
tests/ed_client_test.py
