Metadata-Version: 2.1
Name: nftl-ed-lms-tools
Version: 0.1.5
Summary: Tool 4 partial Ed LMS API handling
Home-page: UNKNOWN
Author: Grzegorz Pawełczuk
Author-email: grzegorz.pawelczuk@nftlearning.com
License: UNKNOWN
Platform: UNKNOWN
Classifier: Programming Language :: Python :: 3
Classifier: License :: OSI Approved :: MIT License
Classifier: Operating System :: OS Independent
